tamar_model_client/__init__.py
tamar_model_client/async_client.py
tamar_model_client/auth.py
tamar_model_client/circuit_breaker.py
tamar_model_client/error_handler.py
tamar_model_client/exceptions.py
tamar_model_client/json_formatter.py
tamar_model_client/logging_icons.py
tamar_model_client/sync_client.py
tamar_model_client/tool_call_helper.py
tamar_model_client/utils.py
tamar_model_client/core/__init__.py
tamar_model_client/core/async_channel_pool.py
tamar_model_client/core/base_client.py
tamar_model_client/core/channel_pool.py
tamar_model_client/core/http_fallback.py
tamar_model_client/core/logging_setup.py
tamar_model_client/core/request_builder.py
tamar_model_client/core/request_id_manager.py
tamar_model_client/core/response_handler.py
tamar_model_client/core/utils.py
tamar_model_client/enums/__init__.py
tamar_model_client/enums/channel.py
tamar_model_client/enums/invoke.py
tamar_model_client/enums/providers.py
tamar_model_client/generated/__init__.py
tamar_model_client/generated/model_service_pb2.py
tamar_model_client/generated/model_service_pb2_grpc.py
tamar_model_client/schemas/__init__.py
tamar_model_client/schemas/inputs.py
tamar_model_client/schemas/outputs.py
tamar_model_client/schemas/inputs/__init__.py
tamar_model_client/schemas/inputs/base.py
tamar_model_client/schemas/inputs/unified.py
tamar_model_client/schemas/inputs/anthropic/__init__.py
tamar_model_client/schemas/inputs/anthropic/messages.py
tamar_model_client/schemas/inputs/azure/__init__.py
tamar_model_client/schemas/inputs/azure/images.py
tamar_model_client/schemas/inputs/bfl/__init__.py
tamar_model_client/schemas/inputs/bfl/flux_images.py
tamar_model_client/schemas/inputs/byteplus/__init__.py
tamar_model_client/schemas/inputs/byteplus/omnihuman_video.py
tamar_model_client/schemas/inputs/byteplus/seedance.py
tamar_model_client/schemas/inputs/fal_ai/__init__.py
tamar_model_client/schemas/inputs/fal_ai/kling_video.py
tamar_model_client/schemas/inputs/fal_ai/qwen_image_edit_multiple_angles.py
tamar_model_client-0.5.2.dist-info/METADATA
tamar_model_client-0.5.2.dist-info/WHEEL
tamar_model_client-0.5.2.dist-info/top_level.txt
tamar_model_client-0.5.2.dist-info/RECORD
