Metadata-Version: 2.4
Name: tamar-model-client
Version: 0.5.2
Summary: A Python SDK for interacting with the Model Manager gRPC service
Home-page: http://gitlab.tamaredge.top/project-tap/AgentOS/model-manager-client
Author: Oscar Ou
Author-email: oscar.ou@tamaredge.ai
Classifier: Programming Language :: Python :: 3.11
Classifier: Programming Language :: Python :: 3.12
Classifier: License :: OSI Approved :: MIT License
Classifier: Operating System :: OS Independent
Requires-Python: >=3.8
Requires-Dist: grpcio~=1.67.1
Requires-Dist: grpcio-tools~=1.67.1
Requires-Dist: pydantic
Requires-Dist: PyJWT
Requires-Dist: nest_asyncio
Requires-Dist: openai==2.8.1
Requires-Dist: google-genai>=1.51.0
Requires-Dist: anthropic>=0.68.0
Requires-Dist: requests>=2.25.0
Requires-Dist: aiohttp>=3.7.0
Dynamic: author
Dynamic: author-email
Dynamic: classifier
Dynamic: description
Dynamic: description-content-type
Dynamic: home-page
Dynamic: requires-dist
Dynamic: requires-python
Dynamic: summary
